wordcounts/__init__.py
wordcounts/plotting.py
wordcounts/wordcounts.py
wordcounts-0.1.0.dist-info/LICENSE
wordcounts-0.1.0.dist-info/WHEEL
wordcounts-0.1.0.dist-info/METADATA
wordcounts-0.1.0.dist-info/RECORD
