Metadata-Version: 2.1
Name: wordcounts
Version: 0.1.0
Summary: This package helps count the number of words in a given text
License: MIT
Author: valli akella
Requires-Python: >=3.9,<4.0
Classifier: License :: OSI Approved :: MIT License
Classifier: Programming Language :: Python :: 3
Classifier: Programming Language :: Python :: 3.10
Classifier: Programming Language :: Python :: 3.9
Requires-Dist: matplotlib (>=3.5.1,<4.0.0)
